<annotation>
	<folder>my-project-name</folder>
	<filename>360_F_304501619_0MN8I6iCeHzd1gdywWumHAsRdfBgrgZi.jpg</filename>
	<path>/my-project-name/360_F_304501619_0MN8I6iCeHzd1gdywWumHAsRdfBgrgZi.jpg</path>
	<source>
		<database>Unspecified</database>
	</source>
	<size>
		<width>838</width>
		<height>360</height>
		<depth>3</depth>
	</size>
	<object>
		<name>Rabbit</name>
		<pose>Unspecified</pose>
		<truncated>0</truncated>
		<difficult>0</difficult>
		<bndbox>
			<xmin>127</xmin>
			<ymin>197</ymin>
			<xmax>237</xmax>
			<ymax>348</ymax>
		</bndbox>
	</object>
	<object>
		<name>Rabbit</name>
		<pose>Unspecified</pose>
		<truncated>0</truncated>
		<difficult>0</difficult>
		<bndbox>
			<xmin>215</xmin>
			<ymin>88</ymin>
			<xmax>331</xmax>
			<ymax>352</ymax>
		</bndbox>
	</object>
	<object>
		<name>Cat</name>
		<pose>Unspecified</pose>
		<truncated>0</truncated>
		<difficult>0</difficult>
		<bndbox>
			<xmin>321</xmin>
			<ymin>56</ymin>
			<xmax>475</xmax>
			<ymax>356</ymax>
		</bndbox>
	</object>
	<object>
		<name>Dog</name>
		<pose>Unspecified</pose>
		<truncated>0</truncated>
		<difficult>0</difficult>
		<bndbox>
			<xmin>456</xmin>
			<ymin>15</ymin>
			<xmax>642</xmax>
			<ymax>354</ymax>
		</bndbox>
	</object>
	<object>
		<name>Dog</name>
		<pose>Unspecified</pose>
		<truncated>0</truncated>
		<difficult>0</difficult>
		<bndbox>
			<xmin>632</xmin>
			<ymin>39</ymin>
			<xmax>789</xmax>
			<ymax>355</ymax>
		</bndbox>
	</object>
</annotation>